setup.py
django_taggee.egg-info/PKG-INFO
django_taggee.egg-info/SOURCES.txt
django_taggee.egg-info/dependency_links.txt
django_taggee.egg-info/not-zip-safe
django_taggee.egg-info/top_level.txt
taggee/__init__.py
taggee/fields.py
taggee/forms.py