Metadata-Version: 1.1
Name: django-taggee
Version: 0.2
Summary: Tag field for Django models
Home-page: https://github.com/koorgoo/django-taggee/
Author: Dima Kurguzov
Author-email: koorgoo@gmail.com
License: MIT
Keywords: django,tag,field
Platform: UNKNOWN
Classifier: Programming Language :: Python
Classifier: Topic :: Software Development :: Libraries :: Python Modules
Classifier: Framework :: Django
Classifier: Environment :: Web Environment
